tfx/__init__.py
tfx/conftest.py
tfx/dependencies.py
tfx/py.typed
tfx/version.py
tfx/components/testdata/__init__.py
tfx/components/testdata/csv_example_gen/Split-eval/data_tfrecord-00000-of-00012.gz
tfx/components/testdata/csv_example_gen/Split-eval/data_tfrecord-00001-of-00012.gz
tfx/components/testdata/csv_example_gen/Split-eval/data_tfrecord-00002-of-00012.gz
tfx/components/testdata/csv_example_gen/Split-eval/data_tfrecord-00003-of-00012.gz
tfx/components/testdata/csv_example_gen/Split-eval/data_tfrecord-00004-of-00012.gz
tfx/components/testdata/csv_example_gen/Split-eval/data_tfrecord-00005-of-00012.gz
tfx/components/testdata/csv_example_gen/Split-eval/data_tfrecord-00006-of-00012.gz
tfx/components/testdata/csv_example_gen/Split-eval/data_tfrecord-00007-of-00012.gz
tfx/components/testdata/csv_example_gen/Split-eval/data_tfrecord-00008-of-00012.gz
tfx/components/testdata/csv_example_gen/Split-eval/data_tfrecord-00009-of-00012.gz
tfx/components/testdata/csv_example_gen/Split-eval/data_tfrecord-00010-of-00012.gz
tfx/components/testdata/csv_example_gen/Split-eval/data_tfrecord-00011-of-00012.gz
tfx/components/testdata/csv_example_gen/Split-train/data_tfrecord-00000-of-00012.gz
tfx/components/testdata/csv_example_gen/Split-train/data_tfrecord-00001-of-00012.gz
tfx/components/testdata/csv_example_gen/Split-train/data_tfrecord-00002-of-00012.gz
tfx/components/testdata/csv_example_gen/Split-train/data_tfrecord-00003-of-00012.gz
tfx/components/testdata/csv_example_gen/Split-train/data_tfrecord-00004-of-00012.gz
tfx/components/testdata/csv_example_gen/Split-train/data_tfrecord-00005-of-00012.gz
tfx/components/testdata/csv_example_gen/Split-train/data_tfrecord-00006-of-00012.gz
tfx/components/testdata/csv_example_gen/Split-train/data_tfrecord-00007-of-00012.gz
tfx/components/testdata/csv_example_gen/Split-train/data_tfrecord-00008-of-00012.gz
tfx/components/testdata/csv_example_gen/Split-train/data_tfrecord-00009-of-00012.gz
ml_pipelines_sdk-1.16.0.dist-info/LICENSE
ml_pipelines_sdk-1.16.0.dist-info/METADATA
ml_pipelines_sdk-1.16.0.dist-info/WHEEL
ml_pipelines_sdk-1.16.0.dist-info/namespace_packages.txt
ml_pipelines_sdk-1.16.0.dist-info/top_level.txt
ml_pipelines_sdk-1.16.0.dist-info/RECORD
