Metadata-Version: 2.1
Name: ml-pipelines-sdk
Version: 1.16.0
Summary: A dependency-light distribution of the core pipeline authoring functionality of TensorFlow Extended (TFX).
Home-page: https://www.tensorflow.org/tfx
Download-URL: https://github.com/tensorflow/tfx/tags
Author-email: Google LLC <tensorflow-extended-dev@googlegroups.com>
License: 
Project-URL: Homepage, https://www.tensorflow.org/tfx
Project-URL: Repository, https://github.com/tensorflow/tfx
Keywords: tensorflow,tfx
Classifier: Development Status :: 5 - Production/Stable
Classifier: Intended Audience :: Developers
Classifier: Intended Audience :: Education
Classifier: Intended Audience :: Science/Research
Classifier: License :: OSI Approved :: Apache Software License
Classifier: Operating System :: OS Independent
Classifier: Programming Language :: Python
Classifier: Programming Language :: Python :: 3
Classifier: Programming Language :: Python :: 3.9
Classifier: Programming Language :: Python :: 3.10
Classifier: Programming Language :: Python :: 3 :: Only
Classifier: Topic :: Scientific/Engineering
Classifier: Topic :: Scientific/Engineering :: Artificial Intelligence
Classifier: Topic :: Scientific/Engineering :: Mathematics
Classifier: Topic :: Software Development
Classifier: Topic :: Software Development :: Libraries
Classifier: Topic :: Software Development :: Libraries :: Python Modules
Requires-Python: <3.11,>=3.9
License-File: LICENSE
Requires-Dist: absl-py<2.0.0,>=0.9
Requires-Dist: ml-metadata<1.17.0,>=1.16.0
Requires-Dist: packaging>=22
Requires-Dist: portpicker<2,>=1.3.1
Requires-Dist: protobuf<5,>=3.20.3
Requires-Dist: docker<8,>=7
Requires-Dist: google-apitools<1,>=0.5
Requires-Dist: google-api-python-client<2,>=1.8
Requires-Dist: jinja2<4,>=2.7.3
Requires-Dist: typing-extensions<5
